Qt5.py
Qt5.py-0.2.0b2.data/data/LICENSE
Qt5.py-0.2.0b2.dist-info/LICENSE
Qt5.py-0.2.0b2.dist-info/METADATA
Qt5.py-0.2.0b2.dist-info/WHEEL
Qt5.py-0.2.0b2.dist-info/top_level.txt
Qt5.py-0.2.0b2.dist-info/RECORD
